{
  "ensemblesize": 20,
  "river_length": 100,
  "timesteps": 300,
  "prop_suitable": 0.5,
  "prop_rejuvenate": 0.2,
  "prop_populated": 0.4,
  "max_habitat_age": 70,
  "p_turnover": 0.05,
  "p_dispersal": 0.6,
  "p_ldd": 0.8,
  "ldd_kernel": [
    0.5,
    0.35,
    0.2,
    0.1,
    0.05
  ],
  "turnoverweights": [
    [
      20,
      0.9
    ],
    [
      50,
      0.5
    ]
  ],
  "flood": {},
  "modelname": "stepstone_",
  "populate_only": [
    0,
    1,
    2,
    3,
    4,
    5,
    6,
    7,
    8,
    9,
    10,
    11,
    12,
    13,
    14,
    15,
    16,
    17,
    18,
    19,
    20,
    21,
    22,
    23,
    24,
    25,
    26,
    27,
    28,
    29,
    30,
    31,
    32,
    33,
    34,
    35,
    36,
    37,
    38
  ],
  "patches_to_verbau": [
    40,
    41,
    42,
    43
  ],
  "stepstone_list": []
}